setup.py
pylinux/__init__.py
pylinux.egg-info/PKG-INFO
pylinux.egg-info/SOURCES.txt
pylinux.egg-info/dependency_links.txt
pylinux.egg-info/requires.txt
pylinux.egg-info/top_level.txt