Metadata-Version: 1.0
Name: pylinux
Version: 0.0.1
Summary: pylinux
Home-page: https://github.com/lvjiyong/pylinux
Author: lvjiyong
Author-email: lvjiyong@gmail.com
License: Apache2.0
Platform: any
